circuit2.v
module circuit2(
  input c,
  input b,
  input a,
  output P
);
  
  assign P = (c & a) | (~c & b);

endmodule

PrimeExample/test.v
module is_prime_TB ();
  reg [2:0] cba;
  wire prime;
  reg pass;

  // circuit DUT_IP(cba[2],cba[1],cba[0],prime);
  circuit2 DUT_IP (cba[2],cba[1],cba[0],prime);
  // circuit3 DUT_IP (cba[2],cba[1],cba[0],prime);
  //  is_prime_procedural DUT_IP(cba[2],cba[1],cba[0],prime);

  initial begin
    $dumpfile("is_prime.vcd");
    $dumpvars(0, is_prime_TB);
    cba  = 0;
    pass = 1;
    #10;
    pass = (prime == 1) ? 0 : pass;
    cba  = 1;
    #10;
    pass = (prime == 1) ? 0 : pass;
    cba  = 2;
    #10;
    pass = (prime == 0) ? 0 : pass;
    cba  = 3;
    #10;
    pass = (prime == 0) ? 0 : pass;
    cba  = 4;
    #10;
    pass = (prime == 1) ? 0 : pass;
    cba  = 5;
    #10;
    pass = (prime == 0) ? 0 : pass;
    cba  = 6;
    #10;
    pass = (prime == 1) ? 0 : pass;
    cba  = 7;
    #10;
    pass = (prime == 0) ? 0 : pass;
    if (pass) $display("\n\nNice job, you aced the Challenge! Pat yourself on the back!\n\n");
    else $display("\n\nThere's something wrong with your module. Don't give up!\n\n");
    $stop;
  end
endmodule

is_prime.vcd
$date
	Tue Jun 24 22:49:09 2025
$end
$version
	Icarus Verilog
$end
$timescale
	1s
$end
$scope module is_prime_TB $end
$var wire 1 ! prime $end
$var reg 3 " cba [2:0] $end
$var reg 1 # pass $end
$scope module DUT_IP $end
$var wire 1 ! P $end
$var wire 1 $ a $end
$var wire 1 % b $end
$var wire 1 & c $end
$upscope $end
$upscope $end
$enddefinitions $end
$comment Show the parameter values. $end
$dumpall
$end
#0
$dumpvars
0&
0%
0$
1#
b0 "
0!
$end
#10
1$
b1 "
#20
1!
1%
0$
b10 "
#30
1$
b11 "
#40
0!
1&
0%
0$
b100 "
#50
1!
1$
b101 "
#60
0!
1%
0$
b110 "
#70
1!
1$
b111 "
