demux_1_to_4.v
module demux_1_to_4 (
    input I,
    input [1:0] sel,
    output reg [3:0] Y
);
    always @(sel, I) begin
        case (sel)
            2'b00: Y = {3'b0, I}; // Output to Y[0]
            2'b01: Y = {2'b0, I, 1'b0}; // Output to Y[1]
            2'b10: Y = {1'b0, I, 2'b0}; // Output to Y[2]
            2'b11: Y = {I, 3'b0}; // Output to Y[3]
        endcase
    end
endmodule

MuxDemux/mux_2_to_1.v
module mux_2_to_1 (
    input [1:0] I,
    input sel,
    output reg Y
);
    always @(sel, I) begin
        if (sel == 0) begin
            Y = I[0];
        end else begin
            Y = I[1];
        end
    end
endmodule

MuxDemux/mux_demux_TB.v
module mux_demux_TB ();

    reg clk_1MHz, clk_4MHz;
    reg sel1;
    reg [1:0] sel2;
    wire mux_out;
    wire [3:0] demux_out;

    // Instantiate the mux_2_to_1 module
    mux_2_to_1 mux_inst (
        .I({clk_1MHz, clk_4MHz}),
        .sel(sel1),
        .Y(mux_out)
    );

    // Instantiate the demux_1_to_4 module
    demux_1_to_4 demux_inst (
        .I(mux_out),
        .sel(sel2),
        .Y(demux_out)
    );  

    // Clock generation
    always #500 clk_1MHz = ~clk_1MHz; // 1 MHz clock
    always #125 clk_4MHz = ~clk_4MHz; // 4 MHz clock

    initial begin
        // save to Gtkwave
        $dumpfile("mux_demux_TB.vcd");
        $dumpvars(0, mux_demux_TB);
        
        clk_1MHz=0;
        clk_4MHz=0;
        sel1=0;
        sel2=0;
        #10_000;
        sel2=1;
        #10_000;
        sel1=1;
        sel2=2;
        #10_000;
        sel2=3;
        #10_000;
        $stop;
    end    
endmodule

mux_demux_TB.vcd
$date
	Wed Jun 25 02:14:11 2025
$end
$version
	Icarus Verilog
$end
$timescale
	1s
$end
$scope module mux_demux_TB $end
$var wire 1 ! mux_out $end
$var wire 4 " demux_out [3:0] $end
$var reg 1 # clk_1MHz $end
$var reg 1 $ clk_4MHz $end
$var reg 1 % sel1 $end
$var reg 2 & sel2 [1:0] $end
$scope module demux_inst $end
$var wire 2 ' sel [1:0] $end
$var wire 1 ! I $end
$var reg 4 ( Y [3:0] $end
$upscope $end
$scope module mux_inst $end
$var wire 2 ) I [1:0] $end
$var wire 1 % sel $end
$var reg 1 ! Y $end
$upscope $end
$upscope $end
$enddefinitions $end
$comment Show the parameter values. $end
$dumpall
$end
#0
$dumpvars
b0 )
b0 (
b0 '
b0 &
0%
0$
0#
b0 "
0!
$end
#125
b1 "
b1 (
1!
b1 )
1$
#250
b0 "
b0 (
0!
b0 )
0$
#375
b1 "
b1 (
1!
b1 )
1$
#500
b0 "
b0 (
0!
0$
b10 )
1#
#625
b1 "
b1 (
1!
b11 )
1$
#750
b0 "
b0 (
0!
b10 )
0$
#875
b1 "
b1 (
1!
b11 )
1$
#1000
b0 "
b0 (
0!
0$
b0 )
0#
#1125
b1 "
b1 (
1!
b1 )
1$
#1250
b0 "
b0 (
0!
b0 )
0$
#1375
b1 "
b1 (
1!
b1 )
1$
#1500
b0 "
b0 (
0!
0$
b10 )
1#
#1625
b1 "
b1 (
1!
b11 )
1$
#1750
b0 "
b0 (
0!
b10 )
0$
#1875
b1 "
b1 (
1!
b11 )
1$
#2000
b0 "
b0 (
0!
0$
b0 )
0#
#2125
b1 "
b1 (
1!
b1 )
1$
#2250
b0 "
b0 (
0!
b0 )
0$
#2375
b1 "
b1 (
1!
b1 )
1$
#2500
b0 "
b0 (
0!
0$
b10 )
1#
#2625
b1 "
b1 (
1!
b11 )
1$
#2750
b0 "
b0 (
0!
b10 )
0$
#2875
b1 "
b1 (
1!
b11 )
1$
#3000
b0 "
b0 (
0!
0$
b0 )
0#
#3125
b1 "
b1 (
1!
b1 )
1$
#3250
b0 "
b0 (
0!
b0 )
0$
#3375
b1 "
b1 (
1!
b1 )
1$
#3500
b0 "
b0 (
0!
0$
b10 )
1#
#3625
b1 "
b1 (
1!
b11 )
1$
#3750
b0 "
b0 (
0!
b10 )
0$
#3875
b1 "
b1 (
1!
b11 )
1$
#4000
b0 "
b0 (
0!
0$
b0 )
0#
#4125
b1 "
b1 (
1!
b1 )
1$
#4250
b0 "
b0 (
0!
b0 )
0$
#4375
b1 "
b1 (
1!
b1 )
1$
#4500
b0 "
b0 (
0!
0$
b10 )
1#
#4625
b1 "
b1 (
1!
b11 )
1$
#4750
b0 "
b0 (
0!
b10 )
0$
#4875
b1 "
b1 (
1!
b11 )
1$
#5000
b0 "
b0 (
0!
0$
b0 )
0#
#5125
b1 "
b1 (
1!
b1 )
1$
#5250
b0 "
b0 (
0!
b0 )
0$
#5375
b1 "
b1 (
1!
b1 )
1$
#5500
b0 "
b0 (
0!
0$
b10 )
1#
#5625
b1 "
b1 (
1!
b11 )
1$
#5750
b0 "
b0 (
0!
b10 )
0$
#5875
b1 "
b1 (
1!
b11 )
1$
#6000
b0 "
b0 (
0!
0$
b0 )
0#
#6125
b1 "
b1 (
1!
b1 )
1$
#6250
b0 "
b0 (
0!
b0 )
0$
#6375
b1 "
b1 (
1!
b1 )
1$
#6500
b0 "
b0 (
0!
0$
b10 )
1#
#6625
b1 "
b1 (
1!
b11 )
1$
#6750
b0 "
b0 (
0!
b10 )
0$
#6875
b1 "
b1 (
1!
b11 )
1$
#7000
b0 "
b0 (
0!
0$
b0 )
0#
#7125
b1 "
b1 (
1!
b1 )
1$
#7250
b0 "
b0 (
0!
b0 )
0$
#7375
b1 "
b1 (
1!
b1 )
1$
#7500
b0 "
b0 (
0!
0$
b10 )
1#
#7625
b1 "
b1 (
1!
b11 )
1$
#7750
b0 "
b0 (
0!
b10 )
0$
#7875
b1 "
b1 (
1!
b11 )
1$
#8000
b0 "
b0 (
0!
0$
b0 )
0#
#8125
b1 "
b1 (
1!
b1 )
1$
#8250
b0 "
b0 (
0!
b0 )
0$
#8375
b1 "
b1 (
1!
b1 )
1$
#8500
b0 "
b0 (
0!
0$
b10 )
1#
#8625
b1 "
b1 (
1!
b11 )
1$
#8750
b0 "
b0 (
0!
b10 )
0$
#8875
b1 "
b1 (
1!
b11 )
1$
#9000
b0 "
b0 (
0!
0$
b0 )
0#
#9125
b1 "
b1 (
1!
b1 )
1$
#9250
b0 "
b0 (
0!
b0 )
0$
#9375
b1 "
b1 (
1!
b1 )
1$
#9500
b0 "
b0 (
0!
0$
b10 )
1#
#9625
b1 "
b1 (
1!
b11 )
1$
#9750
b0 "
b0 (
0!
b10 )
0$
#9875
b1 "
b1 (
1!
b11 )
1$
#10000
0!
b0 "
b0 (
0$
b0 )
0#
b1 &
b1 '
#10125
b10 "
b10 (
1!
b1 )
1$
#10250
b0 "
b0 (
0!
b0 )
0$
#10375
b10 "
b10 (
1!
b1 )
1$
#10500
b0 "
b0 (
0!
0$
b10 )
1#
#10625
b10 "
b10 (
1!
b11 )
1$
#10750
b0 "
b0 (
0!
b10 )
0$
#10875
b10 "
b10 (
1!
b11 )
1$
#11000
b0 "
b0 (
0!
0$
b0 )
0#
#11125
b10 "
b10 (
1!
b1 )
1$
#11250
b0 "
b0 (
0!
b0 )
0$
#11375
b10 "
b10 (
1!
b1 )
1$
#11500
b0 "
b0 (
0!
0$
b10 )
1#
#11625
b10 "
b10 (
1!
b11 )
1$
#11750
b0 "
b0 (
0!
b10 )
0$
#11875
b10 "
b10 (
1!
b11 )
1$
#12000
b0 "
b0 (
0!
0$
b0 )
0#
#12125
b10 "
b10 (
1!
b1 )
1$
#12250
b0 "
b0 (
0!
b0 )
0$
#12375
b10 "
b10 (
1!
b1 )
1$
#12500
b0 "
b0 (
0!
0$
b10 )
1#
#12625
b10 "
b10 (
1!
b11 )
1$
#12750
b0 "
b0 (
0!
b10 )
0$
#12875
b10 "
b10 (
1!
b11 )
1$
#13000
b0 "
b0 (
0!
0$
b0 )
0#
#13125
b10 "
b10 (
1!
b1 )
1$
#13250
b0 "
b0 (
0!
b0 )
0$
#13375
b10 "
b10 (
1!
b1 )
1$
#13500
b0 "
b0 (
0!
0$
b10 )
1#
#13625
b10 "
b10 (
1!
b11 )
1$
#13750
b0 "
b0 (
0!
b10 )
0$
#13875
b10 "
b10 (
1!
b11 )
1$
#14000
b0 "
b0 (
0!
0$
b0 )
0#
#14125
b10 "
b10 (
1!
b1 )
1$
#14250
b0 "
b0 (
0!
b0 )
0$
#14375
b10 "
b10 (
1!
b1 )
1$
#14500
b0 "
b0 (
0!
0$
b10 )
1#
#14625
b10 "
b10 (
1!
b11 )
1$
#14750
b0 "
b0 (
0!
b10 )
0$
#14875
b10 "
b10 (
1!
b11 )
1$
#15000
b0 "
b0 (
0!
0$
b0 )
0#
#15125
b10 "
b10 (
1!
b1 )
1$
#15250
b0 "
b0 (
0!
b0 )
0$
#15375
b10 "
b10 (
1!
b1 )
1$
#15500
b0 "
b0 (
0!
0$
b10 )
1#
#15625
b10 "
b10 (
1!
b11 )
1$
#15750
b0 "
b0 (
0!
b10 )
0$
#15875
b10 "
b10 (
1!
b11 )
1$
#16000
b0 "
b0 (
0!
0$
b0 )
0#
#16125
b10 "
b10 (
1!
b1 )
1$
#16250
b0 "
b0 (
0!
b0 )
0$
#16375
b10 "
b10 (
1!
b1 )
1$
#16500
b0 "
b0 (
0!
0$
b10 )
1#
#16625
b10 "
b10 (
1!
b11 )
1$
#16750
b0 "
b0 (
0!
b10 )
0$
#16875
b10 "
b10 (
1!
b11 )
1$
#17000
b0 "
b0 (
0!
0$
b0 )
0#
#17125
b10 "
b10 (
1!
b1 )
1$
#17250
b0 "
b0 (
0!
b0 )
0$
#17375
b10 "
b10 (
1!
b1 )
1$
#17500
b0 "
b0 (
0!
0$
b10 )
1#
#17625
b10 "
b10 (
1!
b11 )
1$
#17750
b0 "
b0 (
0!
b10 )
0$
#17875
b10 "
b10 (
1!
b11 )
1$
#18000
b0 "
b0 (
0!
0$
b0 )
0#
#18125
b10 "
b10 (
1!
b1 )
1$
#18250
b0 "
b0 (
0!
b0 )
0$
#18375
b10 "
b10 (
1!
b1 )
1$
#18500
b0 "
b0 (
0!
0$
b10 )
1#
#18625
b10 "
b10 (
1!
b11 )
1$
#18750
b0 "
b0 (
0!
b10 )
0$
#18875
b10 "
b10 (
1!
b11 )
1$
#19000
b0 "
b0 (
0!
0$
b0 )
0#
#19125
b10 "
b10 (
1!
b1 )
1$
#19250
b0 "
b0 (
0!
b0 )
0$
#19375
b10 "
b10 (
1!
b1 )
1$
#19500
b0 "
b0 (
0!
0$
b10 )
1#
#19625
b10 "
b10 (
1!
b11 )
1$
#19750
b0 "
b0 (
0!
b10 )
0$
#19875
b10 "
b10 (
1!
b11 )
1$
#20000
b0 "
b0 (
0!
0$
b0 )
0#
b10 &
b10 '
1%
#20125
b1 )
1$
#20250
b0 )
0$
#20375
b1 )
1$
#20500
b100 "
b100 (
1!
0$
b10 )
1#
#20625
b11 )
1$
#20750
b10 )
0$
#20875
b11 )
1$
#21000
b0 "
b0 (
0!
0$
b0 )
0#
#21125
b1 )
1$
#21250
b0 )
0$
#21375
b1 )
1$
#21500
b100 "
b100 (
1!
0$
b10 )
1#
#21625
b11 )
1$
#21750
b10 )
0$
#21875
b11 )
1$
#22000
b0 "
b0 (
0!
0$
b0 )
0#
#22125
b1 )
1$
#22250
b0 )
0$
#22375
b1 )
1$
#22500
b100 "
b100 (
1!
0$
b10 )
1#
#22625
b11 )
1$
#22750
b10 )
0$
#22875
b11 )
1$
#23000
b0 "
b0 (
0!
0$
b0 )
0#
#23125
b1 )
1$
#23250
b0 )
0$
#23375
b1 )
1$
#23500
b100 "
b100 (
1!
0$
b10 )
1#
#23625
b11 )
1$
#23750
b10 )
0$
#23875
b11 )
1$
#24000
b0 "
b0 (
0!
0$
b0 )
0#
#24125
b1 )
1$
#24250
b0 )
0$
#24375
b1 )
1$
#24500
b100 "
b100 (
1!
0$
b10 )
1#
#24625
b11 )
1$
#24750
b10 )
0$
#24875
b11 )
1$
#25000
b0 "
b0 (
0!
0$
b0 )
0#
#25125
b1 )
1$
#25250
b0 )
0$
#25375
b1 )
1$
#25500
b100 "
b100 (
1!
0$
b10 )
1#
#25625
b11 )
1$
#25750
b10 )
0$
#25875
b11 )
1$
#26000
b0 "
b0 (
0!
0$
b0 )
0#
#26125
b1 )
1$
#26250
b0 )
0$
#26375
b1 )
1$
#26500
b100 "
b100 (
1!
0$
b10 )
1#
#26625
b11 )
1$
#26750
b10 )
0$
#26875
b11 )
1$
#27000
b0 "
b0 (
0!
0$
b0 )
0#
#27125
b1 )
1$
#27250
b0 )
0$
#27375
b1 )
1$
#27500
b100 "
b100 (
1!
0$
b10 )
1#
#27625
b11 )
1$
#27750
b10 )
0$
#27875
b11 )
1$
#28000
b0 "
b0 (
0!
0$
b0 )
0#
#28125
b1 )
1$
#28250
b0 )
0$
#28375
b1 )
1$
#28500
b100 "
b100 (
1!
0$
b10 )
1#
#28625
b11 )
1$
#28750
b10 )
0$
#28875
b11 )
1$
#29000
b0 "
b0 (
0!
0$
b0 )
0#
#29125
b1 )
1$
#29250
b0 )
0$
#29375
b1 )
1$
#29500
b100 "
b100 (
1!
0$
b10 )
1#
#29625
b11 )
1$
#29750
b10 )
0$
#29875
b11 )
1$
#30000
0!
b0 "
b0 (
0$
b0 )
0#
b11 &
b11 '
#30125
b1 )
1$
#30250
b0 )
0$
#30375
b1 )
1$
#30500
b1000 "
b1000 (
1!
0$
b10 )
1#
#30625
b11 )
1$
#30750
b10 )
0$
#30875
b11 )
1$
#31000
b0 "
b0 (
0!
0$
b0 )
0#
#31125
b1 )
1$
#31250
b0 )
0$
#31375
b1 )
1$
#31500
b1000 "
b1000 (
1!
0$
b10 )
1#
#31625
b11 )
1$
#31750
b10 )
0$
#31875
b11 )
1$
#32000
b0 "
b0 (
0!
0$
b0 )
0#
#32125
b1 )
1$
#32250
b0 )
0$
#32375
b1 )
1$
#32500
b1000 "
b1000 (
1!
0$
b10 )
1#
#32625
b11 )
1$
#32750
b10 )
0$
#32875
b11 )
1$
#33000
b0 "
b0 (
0!
0$
b0 )
0#
#33125
b1 )
1$
#33250
b0 )
0$
#33375
b1 )
1$
#33500
b1000 "
b1000 (
1!
0$
b10 )
1#
#33625
b11 )
1$
#33750
b10 )
0$
#33875
b11 )
1$
#34000
b0 "
b0 (
0!
0$
b0 )
0#
#34125
b1 )
1$
#34250
b0 )
0$
#34375
b1 )
1$
#34500
b1000 "
b1000 (
1!
0$
b10 )
1#
#34625
b11 )
1$
#34750
b10 )
0$
#34875
b11 )
1$
#35000
b0 "
b0 (
0!
0$
b0 )
0#
#35125
b1 )
1$
#35250
b0 )
0$
#35375
b1 )
1$
#35500
b1000 "
b1000 (
1!
0$
b10 )
1#
#35625
b11 )
1$
#35750
b10 )
0$
#35875
b11 )
1$
#36000
b0 "
b0 (
0!
0$
b0 )
0#
#36125
b1 )
1$
#36250
b0 )
0$
#36375
b1 )
1$
#36500
b1000 "
b1000 (
1!
0$
b10 )
1#
#36625
b11 )
1$
#36750
b10 )
0$
#36875
b11 )
1$
#37000
b0 "
b0 (
0!
0$
b0 )
0#
#37125
b1 )
1$
#37250
b0 )
0$
#37375
b1 )
1$
#37500
b1000 "
b1000 (
1!
0$
b10 )
1#
#37625
b11 )
1$
#37750
b10 )
0$
#37875
b11 )
1$
#38000
b0 "
b0 (
0!
0$
b0 )
0#
#38125
b1 )
1$
#38250
b0 )
0$
#38375
b1 )
1$
#38500
b1000 "
b1000 (
1!
0$
b10 )
1#
#38625
b11 )
1$
#38750
b10 )
0$
#38875
b11 )
1$
#39000
b0 "
b0 (
0!
0$
b0 )
0#
#39125
b1 )
1$
#39250
b0 )
0$
#39375
b1 )
1$
#39500
b1000 "
b1000 (
1!
0$
b10 )
1#
#39625
b11 )
1$
#39750
b10 )
0$
#39875
b11 )
1$
