halfAdder.v
module halfAdder(
	input A,
	input B,
	output S,
	output Cout
);

	and(Cout, A, B);
	xor(S, A, B);
endmodule

fullAdder.v
module fullAdder(
    input A, 
    input B, 
    input Cin, 
    output S, 
    output Cout
	);

	wire P, G, H;
	halfAdder ha1(A,B,P,G);
	halfAdder ha2(P,Cin,S,H);
	// // Otra forma de instanciar
	// // No tiene que respetarse el
	// // Orden
	// half_adder ha2(
	// 	.A(P),
	// 	.B(Cin),
	// 	.S(S),
	// 	.Cout(H)
	// );

	or(Cout, G, H);

endmodule

FullAdder/sim_fullAdder.v
module sim_full_adder ();

    reg a,b,c;
    wire [1:0] s;

    fullAdder fa1(
        .A(a),
        .B(b),
        .Cin(c),
        .S(s[0]),
        .Cout(s[1])
    );

    initial begin
        $dumpfile("fullAdder.vcd");
        $dumpvars(0, sim_full_adder);
        {a, b, c} = 0; #5;
        {a, b, c} = 1; #5;
        {a, b, c} = 2; #5;
        {a, b, c} = 3; #5;
        {a, b, c} = 4; #5;
        {a, b, c} = 5; #5;
        {a, b, c} = 6; #5;
        {a, b, c} = 7; #5;
        $stop;
    end
    
endmodule

FullAdder/fullAdder.vcd
$date
	Wed Jun 25 00:13:09 2025
$end
$version
	Icarus Verilog
$end
$timescale
	1s
$end
$scope module sim_full_adder $end
$var wire 2 ! s [1:0] $end
$var reg 1 " a $end
$var reg 1 # b $end
$var reg 1 $ c $end
$scope module fa1 $end
$var wire 1 " A $end
$var wire 1 # B $end
$var wire 1 $ Cin $end
$var wire 1 % Cout $end
$var wire 1 & S $end
$var wire 1 ' P $end
$var wire 1 ( H $end
$var wire 1 ) G $end
$scope module ha1 $end
$var wire 1 " A $end
$var wire 1 # B $end
$var wire 1 ) Cout $end
$var wire 1 ' S $end
$upscope $end
$scope module ha2 $end
$var wire 1 ' A $end
$var wire 1 $ B $end
$var wire 1 ( Cout $end
$var wire 1 & S $end
$upscope $end
$upscope $end
$upscope $end
$enddefinitions $end
$comment Show the parameter values. $end
$dumpall
$end
#0
$dumpvars
0)
0(
0'
0&
0%
0$
0#
0"
b0 !
$end
#5
b1 !
1&
1$
#10
1'
b1 !
1&
1#
0$
#15
1%
1(
b10 !
0&
1$
#20
0%
0(
b1 !
1&
1"
0#
0$
#25
1%
1(
b10 !
0&
1$
#30
1)
0'
0(
b10 !
0&
1#
0$
#35
b11 !
1&
1$
