Basic/oneFileModules.v
module operations (
    input A,
    input B,
    input C,
    output S
);

    wire w1;

    twoOperations op1(
        .A(A),
        .B(B),
        .S(w1)
    );
    twoOperations op2(
        .A(w1),
        .B(C),
        .S(S)
    );

endmodule

module twoOperations (
    input A,
    input B,    
    output S
);
    wire w1;
    not(w1, A);
    and(S, w1, B);
endmodule

Basic/oneFileModules_TB.v
// Test bench for the operations module in oneFileModules.v
`timescale 1ns / 1ps

module operations_TB;

    // Inputs
    reg A;
    reg B;
    reg C;
    
    // Outputs
    wire S;
    
    // Instantiate the Unit Under Test (UUT)
    operations uut (
        .A(A),
        .B(B),
        .C(C),
        .S(S)
    );
    
    // Test procedure
    initial begin
        // Initialize inputs
        A = 0;
        B = 0;
        C = 0;
        
        // Display header
        $display("Time\tA\tB\tC\tS");
        $display("----\t-\t-\t-\t-");
        
        // Monitor changes
        $monitor("%0t\t%b\t%b\t%b\t%b", $time, A, B, C, S);
        
        // Test all possible input combinations
        #10 A = 0; B = 0; C = 0;  // Expected S = 0 (since A=0, ~A=1, but B=0)
        #10 A = 0; B = 0; C = 1;  // Expected S = 0 (since B=0)
        #10 A = 0; B = 1; C = 0;  // Expected S = 0 (since C=0)
        #10 A = 0; B = 1; C = 1;  // Expected S = 1 (since ~A=1, B=1, C=1)
        #10 A = 1; B = 0; C = 0;  // Expected S = 0 (since ~A=0)
        #10 A = 1; B = 0; C = 1;  // Expected S = 0 (since ~A=0)
        #10 A = 1; B = 1; C = 0;  // Expected S = 0 (since ~A=0)
        #10 A = 1; B = 1; C = 1;  // Expected S = 0 (since ~A=0)
        
        // Additional test with delays to verify behavior
        #10 $display("\nAdditional verification tests:");
        #10 A = 0; B = 1; C = 1;  // This should produce S = 1
        #5  $display("Expected: S=1, Actual: S=%b", S);
        
        #10 A = 1; B = 1; C = 1;  // This should produce S = 0
        #5  $display("Expected: S=0, Actual: S=%b", S);
        
        #10 $display("\nTest completed!");
        $finish;
    end
    
    // Optional: Generate VCD file for waveform viewing
    initial begin
        $dumpfile("oneFileModules_TB.vcd");
        $dumpvars(0, operations_TB);
    end

endmodule

Basic/oneFileModules_TB.vcd
$date
	Thu Jun 26 21:30:26 2025
$end
$version
	Icarus Verilog
$end
$timescale
	1ps
$end
$scope module operations_TB $end
$var wire 1 ! S $end
$var reg 1 " A $end
$var reg 1 # B $end
$var reg 1 $ C $end
$scope module uut $end
$var wire 1 " A $end
$var wire 1 # B $end
$var wire 1 $ C $end
$var wire 1 % w1 $end
$var wire 1 ! S $end
$scope module op1 $end
$var wire 1 " A $end
$var wire 1 # B $end
$var wire 1 % S $end
$var wire 1 & w1 $end
$upscope $end
$scope module op2 $end
$var wire 1 % A $end
$var wire 1 $ B $end
$var wire 1 ! S $end
$var wire 1 ' w1 $end
$upscope $end
$upscope $end
$upscope $end
$enddefinitions $end
$comment Show the parameter values. $end
$dumpall
$end
#0
$dumpvars
1'
1&
0%
0$
0#
0"
0!
$end
#20000
1!
1$
#30000
0'
0!
1%
0$
1#
#40000
1$
#50000
1'
0%
0&
0$
0#
1"
#60000
1!
1$
#70000
0!
0$
1#
#80000
1!
1$
#100000
0!
0'
1%
1&
0"
#115000
1!
1'
0%
0&
1"
