Combinational/ALU.v
module ALU(
	input [3:0] a,
	input [3:0] b,
	input [1:0] op,
	output reg [7:0] result
);

    always @(a, b, op) begin
        case (op)
            2'b00: result = a + b;          // Addition: 
            2'b01: result = a * b;          // Addition: 
            2'b10: result = a % b;          // Addition: 
            2'b11: result = a & b;          // Addition: 
        endcase       
    end
endmodule

Combinational/ALU_TB.v
module ALU_TB();

    // Inputs
    reg [3:0] a;
    reg [3:0] b;
    reg [1:0] op;

    // Outputs
    wire [7:0] result;

    // Instantiate the Unit Under Test (UUT)
    ALU uut (
        .a(a),
        .b(b),
        .op(op),
        .result(result)
    );

    // Test procedure
    initial begin
        // Initialize inputs
        a = 4'b0000;
        b = 4'b0000;
        op = 2'b00;

        // Display header
        $display("Time\tA\tB\tOp\tResult");
        $display("----\t-\t-\t--\t------");

        // Monitor changes
        $monitor("%0t\t%b\t%b\t%b\t%b", $time, a, b, op, result);

        // Test 4 operation for all operations 
        #10 $display("Operacion 1: Addition");
        #10 a = 4'b0000; b = 4'b0000; op = 2'b00;  // Expected Result = 4'b0000 (0 + 0)
        #10 a = 4'b0001; b = 4'b0010; op = 2'b00;  // Expected Result = 4'b0011 (1 + 2)
        #10 a = 4'b0000; b = 4'b0001; op = 2'b00;  // Expected Result = 4'b0001 (0 + 1)
        #10 a = 4'b0011; b = 4'b0001; op = 2'b00;  // Expected Result = 4'b0100 (3 + 1)

        #10 $display("Operacion 2: Multiplication");
        #10 a = 4'b0001; b = 4'b0001; op = 2'b01;  // Expected Result = 4'b0001 (1 * 1)
        #10 a = 4'b0010; b = 4'b0001; op = 2'b01;  // Expected Result = 4'b0010 (2 * 1)
        #10 a = 4'b0001; b = 4'b0000; op = 2'b01;  // Expected Result = 4'b0000 (1 * 0)
        #10 a = 4'd14; b = 4'd10; op = 2'b01;      // Expected Result = 4'd140 (10 * 14)

        #10 $display("Operacion 3: Modulo");
        #10 a = 4'b0010; b = 4'b0001; op = 2'b10;  // Expected Result = 4'b0000 (2 % 1)
        #10 a = 4'b0100; b = 4'b0010; op = 2'b10;  // Expected Result = 4'b0000 (4 % 2)
        #10 a = 4'b0011; b = 4'b0010; op = 2'b10;  // Expected Result = 4'b0001 (3 % 2)
        #10 a = 4'b1100; b = 4'b0011; op = 2'b10;  // Expected Result = 4'b0000 (12 % 3)

        #10 $display("Operacion 4: AND");
        #10 a = 4'b0011; b = 4'b0011; op = 2'b11;  // Expected Result = 4'b0011 (3 & 3)
        #10 a = 4'b0100; b = 4'b0011; op = 2'b11;  // Expected Result = 4'b0000 (4 & 3)
        #10 a = 4'b0010; b = 4'b0001; op = 2'b11;  // Expected Result = 4'b0000 (2 & 1)
        #10 a = 4'b1100; b = 4'b1010; op = 2'b11;  // Expected Result = 4'b1000 (12 & 10)

        #10 $display("\nTest completed!");
        $finish;
    end

    // Optional: Generate VCD file for waveform viewing
    initial begin
        $dumpfile("ALU_TB.vcd");
        $dumpvars(0, ALU_TB);
    end
endmodule

Combinational/ALU_TB.vcd
$date
	Thu Jun 26 22:43:47 2025
$end
$version
	Icarus Verilog
$end
$timescale
	1s
$end
$scope module ALU_TB $end
$var wire 8 ! result [7:0] $end
$var reg 4 " a [3:0] $end
$var reg 4 # b [3:0] $end
$var reg 2 $ op [1:0] $end
$scope module uut $end
$var wire 4 % a [3:0] $end
$var wire 4 & b [3:0] $end
$var wire 2 ' op [1:0] $end
$var reg 8 ( result [7:0] $end
$upscope $end
$upscope $end
$enddefinitions $end
$comment Show the parameter values. $end
$dumpall
$end
#0
$dumpvars
b0 (
b0 '
b0 &
b0 %
b0 $
b0 #
b0 "
b0 !
$end
#30
b11 !
b11 (
b10 #
b10 &
b1 "
b1 %
#40
b1 !
b1 (
b1 #
b1 &
b0 "
b0 %
#50
b100 !
b100 (
b11 "
b11 %
#70
b1 !
b1 (
b1 $
b1 '
b1 "
b1 %
#80
b10 !
b10 (
b10 "
b10 %
#90
b0 !
b0 (
b0 #
b0 &
b1 "
b1 %
#100
b10001100 !
b10001100 (
b1010 #
b1010 &
b1110 "
b1110 %
#120
b0 !
b0 (
b10 $
b10 '
b1 #
b1 &
b10 "
b10 %
#130
b10 #
b10 &
b100 "
b100 %
#140
b1 !
b1 (
b11 "
b11 %
#150
b0 !
b0 (
b11 #
b11 &
b1100 "
b1100 %
#170
b11 !
b11 (
b11 $
b11 '
b11 "
b11 %
#180
b0 !
b0 (
b100 "
b100 %
#190
b1 #
b1 &
b10 "
b10 %
#200
b1000 !
b1000 (
b1010 #
b1010 &
b1100 "
b1100 %
